panta/__init__.py
panta/add_sample_pipeline.py
panta/cli.py
panta/data_preparation.py
panta/main_pipeline.py
panta/output.py
panta/post_analysis.py
panta/utils.py
panta-1.0.1.dist-info/LICENSE
panta-1.0.1.dist-info/METADATA
panta-1.0.1.dist-info/WHEEL
panta-1.0.1.dist-info/entry_points.txt
panta-1.0.1.dist-info/top_level.txt
panta-1.0.1.dist-info/zip-safe
panta-1.0.1.dist-info/RECORD
