Metadata-Version: 2.1
Name: panta
Version: 1.0.1
Summary: PanTA
License-File: LICENSE
